LICENSE
MANIFEST.in
README.md
setup.py
simplediff/__init__.py
simplediff.egg-info/PKG-INFO
simplediff.egg-info/SOURCES.txt
simplediff.egg-info/dependency_links.txt
simplediff.egg-info/top_level.txt
simplediff.egg-info/zip-safe